bm25_rs-1.0.4.dist-info/METADATA
bm25_rs-1.0.4.dist-info/WHEEL
bm25_rs-1.0.4.dist-info/licenses/LICENSE
bm25_rs/__init__.py
bm25_rs/_bm25_rs.cpython-311-darwin.so
bm25_rs/benchmarks.py
bm25_rs/utils.py
bm25_rs-1.0.4.dist-info/RECORD
