Metadata-Version: 2.4
Name: bm25-rs
Version: 1.0.4
Classifier: Development Status :: 4 - Beta
Classifier: Intended Audience :: Developers
Classifier: Intended Audience :: Science/Research
Classifier: License :: OSI Approved :: MIT License
Classifier: Operating System :: OS Independent
Classifier: Programming Language :: Python :: 3
Classifier: Programming Language :: Python :: 3.8
Classifier: Programming Language :: Python :: 3.9
Classifier: Programming Language :: Python :: 3.10
Classifier: Programming Language :: Python :: 3.11
Classifier: Programming Language :: Python :: 3.12
Classifier: Programming Language :: Python :: 3.13
Classifier: Programming Language :: Python :: Implementation :: CPython
Classifier: Programming Language :: Python :: Implementation :: PyPy
Classifier: Programming Language :: Rust
Classifier: Topic :: Scientific/Engineering :: Information Analysis
Classifier: Topic :: Software Development :: Libraries :: Python Modules
Classifier: Topic :: Text Processing :: Indexing
Requires-Dist: pytest>=8.3.5
Requires-Dist: twine>=6.1.0
Requires-Dist: pytest>=7.0 ; extra == 'dev'
Requires-Dist: pytest-benchmark>=4.0 ; extra == 'dev'
Requires-Dist: black>=22.0 ; extra == 'dev'
Requires-Dist: ruff>=0.1.0 ; extra == 'dev'
Requires-Dist: mypy>=1.0 ; extra == 'dev'
Requires-Dist: psutil>=5.8.0 ; extra == 'benchmark'
Requires-Dist: matplotlib>=3.5.0 ; extra == 'benchmark'
Requires-Dist: numpy>=1.21.0 ; extra == 'benchmark'
Provides-Extra: dev
Provides-Extra: benchmark
License-File: LICENSE
Summary: High-performance BM25 implementation in Rust with Python bindings
Keywords: bm25,search,information-retrieval,rust,performance
Home-Page: https://github.com/dorianbrown/rank_bm25
Author-email: BM25-RS Contributors <maintainers@example.com>
Maintainer-email: BM25-RS Contributors <maintainers@example.com>
License: MIT
Requires-Python: >=3.8
Project-URL: Homepage, https://github.com/dorianbrown/rank_bm25
Project-URL: Documentation, https://github.com/dorianbrown/rank_bm25#readme
Project-URL: Repository, https://github.com/dorianbrown/rank_bm25.git
Project-URL: Bug Tracker, https://github.com/dorianbrown/rank_bm25/issues
Project-URL: Changelog, https://github.com/dorianbrown/rank_bm25/blob/main/CHANGELOG.md
